Tavishi_101903046/__init__.py
Tavishi_101903046/topsis.py
Tavishi_101903046-4.1.1.dist-info/METADATA
Tavishi_101903046-4.1.1.dist-info/WHEEL
Tavishi_101903046-4.1.1.dist-info/top_level.txt
Tavishi_101903046-4.1.1.dist-info/RECORD
