Metadata-Version: 2.1
Name: Tavishi-101903046
Version: 4.1.1
Summary: Topsis score rank generator
Home-page: https://github.com/Tavishi18/101903046
Author: The Enchanted Carrot
Author-email: tsharma1_be19@thapar.edu
License: UNKNOWN
Platform: UNKNOWN
Classifier: Programming Language :: Python :: 3
Classifier: License :: OSI Approved :: MIT License
Classifier: Operating System :: OS Independent
